fa_material/__init__.py
fa_material/plugin.py
fa_material-1.1.0.dist-info/LICENSE.md
fa_material-1.1.0.dist-info/METADATA
fa_material-1.1.0.dist-info/WHEEL
fa_material-1.1.0.dist-info/entry_points.txt
fa_material-1.1.0.dist-info/RECORD
