Metadata-Version: 2.1
Name: fa-material
Version: 1.1.0
Summary: Font Awesome Pro + Material for MkDocs
License: MIT
Author: celsius narhwal
Author-email: hello@celsiusnarhwal.dev
Requires-Python: >=3.7,<4.0
Classifier: License :: OSI Approved :: MIT License
Classifier: Programming Language :: Python :: 3
Classifier: Programming Language :: Python :: 3.7
Classifier: Programming Language :: Python :: 3.8
Classifier: Programming Language :: Python :: 3.9
Classifier: Programming Language :: Python :: 3.10
Classifier: Programming Language :: Python :: 3.11
Requires-Dist: dict-deep (>=4.1.2,<5.0.0)
Requires-Dist: fontawesome-pro (>=5.15.4,<6.0.0)
Requires-Dist: mkdocs (>=1.4.2,<2.0.0)
Requires-Dist: path (>=16.6.0,<17.0.0)
